.gitignore
LICENSE.md
README.md
pyproject.toml
setup.py
src/core.pyx
src/monotonic_align/__init__.py
src/monotonic_align.egg-info/PKG-INFO
src/monotonic_align.egg-info/SOURCES.txt
src/monotonic_align.egg-info/dependency_links.txt
src/monotonic_align.egg-info/top_level.txt