Metadata-Version: 2.1
Name: monotonic-align
Version: 1.0.0
Summary: Monotonic Alignment Search module
Author-email: Moonsik Park <moonsik.park@estsoft.com>
Project-URL: repository, https://github.com/moonsikpark/monotonic_align
Classifier: Development Status :: 5 - Production/Stable
Classifier: License :: OSI Approved :: MIT License
Classifier: Operating System :: OS Independent
Classifier: Programming Language :: Python :: 3
Classifier: Programming Language :: Cython
Classifier: Topic :: Scientific/Engineering :: Artificial Intelligence
Requires-Python: >=3.7
License-File: LICENSE.md
